odoo/addons/l10n_mx_sat_account/README.rst
odoo/addons/l10n_mx_sat_account/__init__.py
odoo/addons/l10n_mx_sat_account/__manifest__.py
odoo/addons/l10n_mx_sat_account/data/account.account.tag.csv
odoo/addons/l10n_mx_sat_account/data/account.account.tag.xml
odoo/addons/l10n_mx_sat_account/i18n/l10n_mx_sat_account.pot
odoo/addons/l10n_mx_sat_account/models/__init__.py
odoo/addons/l10n_mx_sat_account/models/account_account.py
odoo/addons/l10n_mx_sat_account/models/account_account_tag.py
odoo/addons/l10n_mx_sat_account/readme/CONTRIBUTORS.rst
odoo/addons/l10n_mx_sat_account/readme/DESCRIPTION.rst
odoo/addons/l10n_mx_sat_account/readme/USAGE.rst
odoo/addons/l10n_mx_sat_account/static/description/icon.png
odoo/addons/l10n_mx_sat_account/static/description/index.html
odoo/addons/l10n_mx_sat_account/views/account_account_tag.xml
odoo13_addon_l10n_mx_sat_account-13.0.1.0.1.dev10.dist-info/METADATA
odoo13_addon_l10n_mx_sat_account-13.0.1.0.1.dev10.dist-info/WHEEL
odoo13_addon_l10n_mx_sat_account-13.0.1.0.1.dev10.dist-info/top_level.txt
odoo13_addon_l10n_mx_sat_account-13.0.1.0.1.dev10.dist-info/RECORD
